{
  "node_id": "PA_PMC-01",
  "state": "PA",
  "state_name": "Pennsylvania",
  "node_family": "PMC",
  "subnode": "PMC-01",
  "trigger_name": "CFSR Monitoring",
  "summary_html": "Federal **Child and Family Services Reviews (CFSR)** monitor state performance on safety, permanency, and well-being. Project Milk Carton flags states that repeatedly fail or never publish CFSR improvement plans.",
  "authority_html": "- **45 CFR Part 1355** \u2014 CFSR procedures and performance metrics  \n- **Social Security Act IV-E (42 U.S.C. \u00a7\u00a7 670\u2013679c)** \u2014 ties funding to CFSR compliance",
  "icon": "\ud83d\udd0d",
  "theme_color": "#1E90FF",
  "domain": "civil",
  "procedural_weight": 0.6,
  "federal_alignment_flag": "baseline",
  "urls": {
    "CFSR_CFR": "https://www.law.cornell.edu/cfr/text/45/part-1355",
    "ACF_CFSR": "https://www.acf.hhs.gov/cb/monitoring/child-family-services-reviews"
  },
  "layers": {
    "constitutional": {
      "constraints_triggered": [],
      "alignment": "aligned"
    },
    "federal": {
      "requirements_applicable": [
        "45 CFR Part 1355 (CFSR)",
        "42 U.S.C. \u00a7\u00a7 670\u2013679c (SSA Title IV-E)"
      ]
    },
    "state_statutory": {
      "primary_citations": [
        {
          "citation_text": "Pennsylvania - Title 23 Pa.C.S. Chapter\u00a063 (Child Protective Services Law)",
          "source_url": "https://law.onecle.com/pennsylvania/title-23/chapter-63/index.html",
          "authority_type": "state_statute",
          "last_verified": "2025-12-22",
          "deep_link": true
        },
        {
          "citation_text": "Pennsylvania - 42 Pa.C.S. Chapter\u00a063 (Juvenile Act \u2013 dependency proceedings)",
          "source_url": "https://www.legis.state.pa.us/cfdocs/legis/LI/consCheck.cfm?txtType=HTM&ttl=4&div=0&chpt=2",
          "authority_type": "state_statute",
          "last_verified": "2025-12-22",
          "deep_link": true
        },
        {
          "citation_text": "Title 23: Domestic Relations - CHILD WELFARE PRIMARY",
          "source_url": "https://law.justia.com/codes/pennsylvania/title-23/",
          "authority_type": "state_statute",
          "last_verified": "2025-12-24",
          "deep_link": true,
          "title_code": "",
          "chapter": ""
        },
        {
          "citation_text": "Title 42: Judiciary - Juvenile Matters",
          "source_url": "https://law.justia.com/codes/pennsylvania/title-42/",
          "authority_type": "state_statute",
          "last_verified": "2025-12-24",
          "deep_link": true,
          "title_code": "",
          "chapter": ""
        },
        {
          "citation_text": "Title 55: Public Welfare",
          "source_url": "https://law.justia.com/codes/pennsylvania/title-55/",
          "authority_type": "state_statute",
          "last_verified": "2025-12-24",
          "deep_link": true,
          "title_code": "",
          "chapter": ""
        },
        {
          "citation_text": "Title 62: Human Services Code",
          "source_url": "https://law.justia.com/codes/pennsylvania/title-62/",
          "authority_type": "state_statute",
          "last_verified": "2025-12-24",
          "deep_link": true,
          "title_code": "",
          "chapter": ""
        }
      ]
    },
    "administrative_rule": {
      "regulations_applicable": [
        {
          "title": "Title 55 - HUMAN SERVICES",
          "url": "https://www.law.cornell.edu/regulations/pennsylvania/title-55"
        },
        {
          "title": "Title 237 - JUVENILE RULES",
          "url": "https://www.law.cornell.edu/regulations/pennsylvania/title-237"
        },
        {
          "title": "Title 246 - MINOR COURT CIVIL RULES",
          "url": "https://www.law.cornell.edu/regulations/pennsylvania/title-246"
        }
      ],
      "source_url": "https://www.law.cornell.edu/regulations/pennsylvania.html"
    },
    "state_constitutional": {
      "plane_reference": "state_constitutional_PA",
      "plane_file": "legal_planes/state_constitutional/PA_constitution.json",
      "provisions_triggered": []
    },
    "case_law": {
      "search_keywords": [
        "Pennsylvania Department of Human Services",
        "Children and Youth Services",
        "CYS",
        "CPS",
        "due process",
        "14th Amendment",
        "42 U.S.C. 1983",
        "reasonable efforts",
        "reunification",
        "emergency removal"
      ],
      "courtlistener_search_url": "https://www.courtlistener.com/?q=%22Pennsylvania%22%20AND%20%28%22Pennsylvania%20Department%20of%20Human%20Services%22%20OR%20%22Children%20and%20Youth%20Services%22%20OR%20%22CYS%22%20OR%20%22CPS%22%20OR%20%22due%20process%22%29&type=o&order_by=score+desc",
      "relevant_case_types": [
        "missing child",
        "amber alert",
        "custodial interference",
        "parental kidnapping"
      ],
      "jurisdiction": "Pennsylvania state courts",
      "key_cases": [
        {
          "case_id": "216-wal-2025",
          "title": "In Re: Blythedale Park of: EQT Artemis - No. (Granted) (petitions for allowance of appeal)",
          "url": "https://law.justia.com/cases/pennsylvania/supreme-court/2025/216-wal-2025.html",
          "year": 2025,
          "court": "Supreme Court",
          "citation": "Pennsylvania Supreme Court Case 216-wal-2025 (2025)",
          "relevance_score": 1.0,
          "matched_keywords": [
            "child welfare"
          ],
          "child_welfare_reason": "High: In re"
        },
        {
          "case_id": "1029-supreme-court-rules",
          "title": "In Re: Appointments to the Orphans' Court Procedural Rules Committee (appointment)",
          "url": "https://law.justia.com/cases/pennsylvania/supreme-court/2025/1029-supreme-court-rules.html",
          "year": 2025,
          "court": "Supreme Court",
          "citation": "Pennsylvania Supreme Court Case 1029-supreme-court-rules (2025)",
          "relevance_score": 1.0,
          "matched_keywords": [
            "child welfare"
          ],
          "child_welfare_reason": "High: In re"
        },
        {
          "case_id": "3093-dd3",
          "title": "In the Matter of: Paul T. Sosnowski (disciplinary order)",
          "url": "https://law.justia.com/cases/pennsylvania/supreme-court/2025/3093-dd3.html",
          "year": 2025,
          "court": "Supreme Court",
          "citation": "Pennsylvania Supreme Court Case 3093-dd3 (2025)",
          "relevance_score": 1.0,
          "matched_keywords": [
            "child welfare"
          ],
          "child_welfare_reason": "High: Matter of"
        },
        {
          "case_id": "471-mal-2025",
          "title": "In Re: Estate of Byerley, D. of: Byerley, D. (petitions for allowance of appeal)",
          "url": "https://law.justia.com/cases/pennsylvania/supreme-court/2025/471-mal-2025.html",
          "year": 2025,
          "court": "Supreme Court",
          "citation": "Pennsylvania Supreme Court Case 471-mal-2025 (2025)",
          "relevance_score": 1.0,
          "matched_keywords": [
            "child welfare"
          ],
          "child_welfare_reason": "High: In re"
        },
        {
          "case_id": "398-judicial-classification",
          "title": "In Re: Reassignment of Honorable Sierra Thomas Street to CCP First Judicial District Orphans' Division (appointment)",
          "url": "https://law.justia.com/cases/pennsylvania/supreme-court/2025/398-judicial-classification.html",
          "year": 2025,
          "court": "Supreme Court",
          "citation": "Pennsylvania Supreme Court Case 398-judicial-classification (2025)",
          "relevance_score": 1.0,
          "matched_keywords": [
            "child welfare"
          ],
          "child_welfare_reason": "High: In re"
        },
        {
          "case_id": "399-judicial-classification",
          "title": "In Re: Reassignment of Honorable Daine A. Grey to CCP First Judicial District Trial Division (appointment)",
          "url": "https://law.justia.com/cases/pennsylvania/supreme-court/2025/399-judicial-classification.html",
          "year": 2025,
          "court": "Supreme Court",
          "citation": "Pennsylvania Supreme Court Case 399-judicial-classification (2025)",
          "relevance_score": 1.0,
          "matched_keywords": [
            "child welfare"
          ],
          "child_welfare_reason": "High: In re"
        },
        {
          "case_id": "65-rst-2025",
          "title": "In the Matter of: James Richard Koban, II (disciplinary order)",
          "url": "https://law.justia.com/cases/pennsylvania/supreme-court/2025/65-rst-2025.html",
          "year": 2025,
          "court": "Supreme Court",
          "citation": "Pennsylvania Supreme Court Case 65-rst-2025 (2025)",
          "relevance_score": 1.0,
          "matched_keywords": [
            "child welfare"
          ],
          "child_welfare_reason": "High: Matter of"
        },
        {
          "case_id": "66-rst-2025",
          "title": "In the Matter of: Jarrod W. Harmon (disciplinary order)",
          "url": "https://law.justia.com/cases/pennsylvania/supreme-court/2025/66-rst-2025.html",
          "year": 2025,
          "court": "Supreme Court",
          "citation": "Pennsylvania Supreme Court Case 66-rst-2025 (2025)",
          "relevance_score": 1.0,
          "matched_keywords": [
            "child welfare"
          ],
          "child_welfare_reason": "High: Matter of"
        },
        {
          "case_id": "648-judicial-administration-2025",
          "title": "In RE: Duty Assignment Schedule for Emergency itions in the Year 2026 (rules)",
          "url": "https://law.justia.com/cases/pennsylvania/supreme-court/2025/648-judicial-administration-2025.html",
          "year": 2025,
          "court": "Supreme Court",
          "citation": "Pennsylvania Supreme Court Case 648-judicial-administration-2025 (2025)",
          "relevance_score": 1.0,
          "matched_keywords": [
            "child welfare"
          ],
          "child_welfare_reason": "High: In re"
        },
        {
          "case_id": "593-mal-2025",
          "title": "In Re: Adopt. of: J.E.M.-M., a Minor (petitions for allowance of appeal)",
          "url": "https://law.justia.com/cases/pennsylvania/supreme-court/2025/593-mal-2025.html",
          "year": 2025,
          "court": "Supreme Court",
          "citation": "Pennsylvania Supreme Court Case 593-mal-2025 (2025)",
          "relevance_score": 1.0,
          "matched_keywords": [
            "child welfare"
          ],
          "child_welfare_reason": "High: In re"
        }
      ],
      "_note": "Use search URL to find relevant cases on CourtListener"
    }
  },
  "state_agency": {
    "name": "Children and Youth Services",
    "acronym": "CYS",
    "hotline": "1-800-932-0313",
    "website": "https://www.legis.state.pa.us"
  },
  "linked_fail": "FAIL-03",
  "_metadata": {
    "created": "2025-12-22T19:33:40.816219",
    "source": "real_data_etl",
    "data_sources": [
      "SCAN_2023",
      "CSE_DomainMap",
      "state_sources",
      "federal_baseline"
    ],
    "federal_baseline": true,
    "state_specific": true,
    "schema_v3_updated": "2025-12-22T22:17:51.794086",
    "schema_version": "3.0.0",
    "trigger_name_fixed": "2025-12-22T22:53:02.417034",
    "leaves_linked": "2025-12-24T18:14:22.343457+00:00",
    "leaf_linker_version": "1.0.0"
  },
  "burden_of_proof": {
    "standard": "probable_cause",
    "who_bears_burden": "agency",
    "common_failures": [
      "Delayed AMBER alert",
      "Failure to coordinate with NCMEC",
      "Inadequate search protocols"
    ]
  },
  "timeline_requirements": [
    {
      "requirement_name": "Missing child report",
      "deadline": "Immediate",
      "starts_from": "Child discovered missing",
      "source": "federal_statute",
      "consequence_of_miss": "Criminal liability possible"
    },
    {
      "requirement_name": "NCMEC notification",
      "deadline": "24 hours",
      "starts_from": "Child reported missing",
      "source": "state_statute",
      "consequence_of_miss": "Audit finding, delayed recovery"
    }
  ],
  "notice_requirements": [
    {
      "who_must_be_notified": [
        "parent",
        "legal_guardian",
        "law_enforcement"
      ],
      "method": "any_reasonable",
      "timing": "Immediately upon discovery",
      "content_required": [
        "Child last seen location",
        "Physical description"
      ],
      "defective_notice_consequence": "Delayed search response"
    }
  ]
}