{
  "node_id": "FL_ACT-04",
  "state": "FL",
  "state_name": "Florida",
  "node_family": "ACT",
  "subnode": "ACT-04",
  "trigger_name": "Kinship Placement",
  "summary_html": "Agency places a child with **relatives or kin caregivers** instead of non-relative foster care. Federal law favors kinship care as least-restrictive, family-preserving placement.",
  "authority_html": "- **Fostering Connections to Success and Increasing Adoptions Act (FCSIAA 2008)** \u2014 kinship-care incentives  \n- **SSA Title IV-E (42 U.S.C. \u00a7\u00a7 670\u2013679c)** \u2014 reimbursement for approved kin placements",
  "icon": "\ud83d\udc68\u200d\ud83d\udc69\u200d\ud83d\udc67",
  "theme_color": "#FFD700",
  "domain": "civil",
  "procedural_weight": 0.45,
  "federal_alignment_flag": "baseline",
  "urls": {
    "FCSIAA_PLAW": "https://www.congress.gov/110/plaws/publ351/PLAW-110publ351.pdf",
    "FCSIAA_PDF": "https://www.govinfo.gov/content/pkg/PLAW-110publ351/pdf/PLAW-110publ351.pdf",
    "SSA_IV_E_Cornell": "https://www.law.cornell.edu/uscode/text/42/chapter-7/subchapter-IV/part-E"
  },
  "layers": {
    "constitutional": {
      "constraints_triggered": [
        "U.S. Const. amend. XIV, \u00a7 1"
      ],
      "alignment": "aligned"
    },
    "federal": {
      "requirements_applicable": [
        "Public Law 110-351 (FCSIAA)",
        "42 U.S.C. \u00a7\u00a7 670\u2013679c (SSA Title IV-E)"
      ]
    },
    "state_statutory": {
      "primary_citations": [
        {
          "citation_text": "Florida - Title V, Chapter 39 (Proceedings Relating to Children \u2013 abuse reporting and CPS)",
          "source_url": "http://www.leg.state.fl.us/statutes/index.cfm?App_mode=Display_Statute&URL=0000-0099/0039/0039.html",
          "authority_type": "state_statute",
          "last_verified": "2025-12-22",
          "deep_link": true
        },
        {
          "citation_text": "Title 39: Proceedings Relating to Children - CHILD WELFARE PRIMARY",
          "source_url": "https://law.justia.com/codes/florida/title-39/",
          "authority_type": "state_statute",
          "last_verified": "2025-12-24",
          "deep_link": true,
          "title_code": "",
          "chapter": ""
        }
      ]
    },
    "administrative_rule": {
      "regulations_applicable": [
        {
          "title": "Department 63 - DEPARTMENT OF JUVENILE JUSTICE",
          "url": "https://www.law.cornell.edu/regulations/florida/department-63"
        },
        {
          "title": "Department 65 - DEPARTMENT OF CHILDREN AND FAMILIES",
          "url": "https://www.law.cornell.edu/regulations/florida/department-65"
        },
        {
          "title": "Florida Administrative Rule Title 39",
          "url": "https://regulations.justia.com/states/florida/title-39/",
          "authority_type": "administrative_rule",
          "last_verified": "2025-12-24"
        },
        {
          "title": "Florida Administrative Rule Title 63",
          "url": "https://regulations.justia.com/states/florida/title-63/",
          "authority_type": "administrative_rule",
          "last_verified": "2025-12-24"
        },
        {
          "title": "Florida Administrative Regulations",
          "url": "https://regulations.justia.com/states/florida/",
          "authority_type": "administrative_rule",
          "last_verified": "2025-12-24"
        },
        {
          "title": "Florida Administrative Rule Title 1",
          "url": "https://regulations.justia.com/states/florida/title-1/",
          "authority_type": "administrative_rule",
          "last_verified": "2025-12-24"
        },
        {
          "title": "Florida Administrative Rule Title 2",
          "url": "https://regulations.justia.com/states/florida/title-2/",
          "authority_type": "administrative_rule",
          "last_verified": "2025-12-24"
        },
        {
          "title": "Florida Administrative Rule Title 3",
          "url": "https://regulations.justia.com/states/florida/title-3/",
          "authority_type": "administrative_rule",
          "last_verified": "2025-12-24"
        },
        {
          "title": "Florida Administrative Rule Title 4",
          "url": "https://regulations.justia.com/states/florida/title-4/",
          "authority_type": "administrative_rule",
          "last_verified": "2025-12-24"
        },
        {
          "title": "Florida Administrative Rule Title 5",
          "url": "https://regulations.justia.com/states/florida/title-5/",
          "authority_type": "administrative_rule",
          "last_verified": "2025-12-24"
        },
        {
          "title": "Florida Administrative Rule Title 6",
          "url": "https://regulations.justia.com/states/florida/title-6/",
          "authority_type": "administrative_rule",
          "last_verified": "2025-12-24"
        },
        {
          "title": "Florida Administrative Rule Title 7",
          "url": "https://regulations.justia.com/states/florida/title-7/",
          "authority_type": "administrative_rule",
          "last_verified": "2025-12-24"
        }
      ],
      "source_url": "https://www.law.cornell.edu/regulations/florida.html"
    },
    "state_constitutional": {
      "plane_reference": "state_constitutional_FL",
      "plane_file": "legal_planes/state_constitutional/FL_constitution.json",
      "provisions_triggered": [
        {
          "provision_id": "FL_CONST_DUE_PROCESS",
          "name": "Due Process / Law of the Land",
          "citation": "Florida Const. art. I, \u00a7 9",
          "federal_parallel": "U.S. Const. amend. XIV, \u00a7 1"
        }
      ]
    },
    "case_law": {
      "search_keywords": [
        "Florida Department of Children and Families",
        "DCF",
        "CPS",
        "due process",
        "14th Amendment",
        "42 U.S.C. 1983",
        "reasonable efforts",
        "reunification",
        "emergency removal",
        "wrongful removal"
      ],
      "courtlistener_search_url": "https://www.courtlistener.com/?q=%22Florida%22%20AND%20%28%22Florida%20Department%20of%20Children%20and%20Families%22%20OR%20%22DCF%22%20OR%20%22CPS%22%20OR%20%22due%20process%22%20OR%20%2214th%20Amendment%22%29&type=o&order_by=score+desc",
      "relevant_case_types": [
        "removal",
        "emergency custody",
        "placement",
        "reunification",
        "services"
      ],
      "jurisdiction": "Florida state courts",
      "key_cases": [
        {
          "case_id": "sc2023-1072",
          "title": "Christine Askew, etc. v. Florida Department of Children and Families",
          "url": "https://law.justia.com/cases/florida/supreme-court/2024/sc2023-1072.html",
          "year": 2024,
          "court": "Supreme Court",
          "citation": "Florida Supreme Court Case sc2023-1072 (2024)",
          "relevance_score": 3.0,
          "matched_keywords": [
            "florida department of children and families",
            "dcf"
          ],
          "child_welfare_reason": "High: DCF"
        },
        {
          "case_id": "sc2024-1403",
          "title": "In Re: Amendments to Florida Rules of General Practice and Judicial Administration",
          "url": "https://law.justia.com/cases/florida/supreme-court/2025/sc2024-1403.html",
          "year": 2025,
          "court": "Supreme Court",
          "citation": "Florida Supreme Court Case sc2024-1403 (2025)",
          "relevance_score": 1.0,
          "matched_keywords": [
            "child welfare"
          ],
          "child_welfare_reason": "High: In re"
        },
        {
          "case_id": "sc2025-1173",
          "title": "In Re: Amendments to Rules Regulating The Florida Bar - Rule 4-8.6",
          "url": "https://law.justia.com/cases/florida/supreme-court/2025/sc2025-1173.html",
          "year": 2025,
          "court": "Supreme Court",
          "citation": "Florida Supreme Court Case sc2025-1173 (2025)",
          "relevance_score": 1.0,
          "matched_keywords": [
            "child welfare"
          ],
          "child_welfare_reason": "High: In re"
        },
        {
          "case_id": "sc2025-1180",
          "title": "In Re: Amendments to Rules Regulating The Florida Bar - Chapter 3",
          "url": "https://law.justia.com/cases/florida/supreme-court/2025/sc2025-1180.html",
          "year": 2025,
          "court": "Supreme Court",
          "citation": "Florida Supreme Court Case sc2025-1180 (2025)",
          "relevance_score": 1.0,
          "matched_keywords": [
            "child welfare"
          ],
          "child_welfare_reason": "High: In re"
        },
        {
          "case_id": "sc2025-1750",
          "title": "In Re: Amendment to Florida Rule of General Practice and Judicial Administration 2.140",
          "url": "https://law.justia.com/cases/florida/supreme-court/2025/sc2025-1750.html",
          "year": 2025,
          "court": "Supreme Court",
          "citation": "Florida Supreme Court Case sc2025-1750 (2025)",
          "relevance_score": 1.0,
          "matched_keywords": [
            "child welfare"
          ],
          "child_welfare_reason": "High: In re"
        },
        {
          "case_id": "sc2025-0530-0",
          "title": "In Re: Amendments to the Florida Rules of Criminal Procedure - 2025 Legislation",
          "url": "https://law.justia.com/cases/florida/supreme-court/2025/sc2025-0530-0.html",
          "year": 2025,
          "court": "Supreme Court",
          "citation": "Florida Supreme Court Case sc2025-0530-0 (2025)",
          "relevance_score": 1.0,
          "matched_keywords": [
            "child welfare"
          ],
          "child_welfare_reason": "High: In re"
        },
        {
          "case_id": "sc2025-1808",
          "title": "In Re: Certification of Need for Additional Judges",
          "url": "https://law.justia.com/cases/florida/supreme-court/2025/sc2025-1808.html",
          "year": 2025,
          "court": "Supreme Court",
          "citation": "Florida Supreme Court Case sc2025-1808 (2025)",
          "relevance_score": 1.0,
          "matched_keywords": [
            "child welfare"
          ],
          "child_welfare_reason": "High: In re"
        },
        {
          "case_id": "sc2025-0017",
          "title": "In Re: Amendments to Rules Regulating The Florida Bar - Rules 6-3.5 and 6-3.6",
          "url": "https://law.justia.com/cases/florida/supreme-court/2025/sc2025-0017.html",
          "year": 2025,
          "court": "Supreme Court",
          "citation": "Florida Supreme Court Case sc2025-0017 (2025)",
          "relevance_score": 1.0,
          "matched_keywords": [
            "child welfare"
          ],
          "child_welfare_reason": "High: In re"
        },
        {
          "case_id": "sc2022-0575",
          "title": "In Re: Amendments to Florida Rules of Civil Procedure 1.440 and 1.500",
          "url": "https://law.justia.com/cases/florida/supreme-court/2025/sc2022-0575.html",
          "year": 2025,
          "court": "Supreme Court",
          "citation": "Florida Supreme Court Case sc2022-0575 (2025)",
          "relevance_score": 1.0,
          "matched_keywords": [
            "child welfare"
          ],
          "child_welfare_reason": "High: In re"
        },
        {
          "case_id": "sc2025-0045",
          "title": "In Re: Amendments to Florida Rule of Civil Procedure 1.442 and Forms 1.902 and 1.938",
          "url": "https://law.justia.com/cases/florida/supreme-court/2025/sc2025-0045.html",
          "year": 2025,
          "court": "Supreme Court",
          "citation": "Florida Supreme Court Case sc2025-0045 (2025)",
          "relevance_score": 1.0,
          "matched_keywords": [
            "child welfare"
          ],
          "child_welfare_reason": "High: In re"
        }
      ],
      "_note": "Use search URL to find relevant cases on CourtListener"
    }
  },
  "state_agency": {
    "name": "Department of Children and Families",
    "acronym": "DCF",
    "hotline": "1-800-962-2873",
    "website": "https://www.leg.state.fl.us"
  },
  "linked_decision": "DEC-04",
  "linked_input": "INP-01",
  "_metadata": {
    "created": "2025-12-22T19:33:40.733485",
    "source": "real_data_etl",
    "data_sources": [
      "SCAN_2023",
      "CSE_DomainMap",
      "state_sources",
      "federal_baseline"
    ],
    "federal_baseline": true,
    "state_specific": true,
    "schema_v3_updated": "2025-12-22T22:17:51.559318",
    "schema_version": "3.0.0",
    "trigger_name_fixed": "2025-12-22T22:53:02.302142",
    "leaves_linked": "2025-12-24T18:14:21.130997+00:00",
    "leaf_linker_version": "1.0.0"
  },
  "burden_of_proof": {
    "standard": "preponderance",
    "who_bears_burden": "agency",
    "common_failures": [
      "Inadequate safety planning",
      "Failure to consider less restrictive alternatives",
      "Insufficient reasonable efforts documentation"
    ]
  },
  "timeline_requirements": [
    {
      "requirement_name": "Emergency removal hearing",
      "deadline": "24-72 hours",
      "starts_from": "Child removed",
      "source": "state_statute",
      "consequence_of_miss": "Constitutional violation, case dismissal"
    },
    {
      "requirement_name": "Case plan development",
      "deadline": "30-60 days",
      "starts_from": "Court jurisdiction",
      "source": "federal_statute",
      "consequence_of_miss": "IV-E funding penalty"
    }
  ],
  "notice_requirements": [
    {
      "who_must_be_notified": [
        "parent",
        "legal_guardian",
        "child_over_12",
        "tribe"
      ],
      "method": "personal_service",
      "timing": "Before court hearing",
      "content_required": [
        "Hearing date",
        "Allegations",
        "Right to counsel"
      ],
      "defective_notice_consequence": "Hearing must be continued"
    }
  ],
  "door_scenarios": [
    {
      "who_at_door": [
        "caseworker",
        "law_enforcement"
      ],
      "trigger_reason": "Emergency removal attempt",
      "legal_authority_to_enter": "exigent_circumstances",
      "parent_rights_at_moment": [
        "Demand to see court order",
        "Right to know where child is going",
        "Right to attorney",
        "Right to hearing within 24-72 hours"
      ],
      "what_to_say": [
        "Do you have a court order for removal?",
        "What is the specific imminent danger?",
        "Where are you taking my child?",
        "I want my attorney present"
      ],
      "what_not_to_do": [
        "Do not physically interfere with lawful removal",
        "Do not flee with child",
        "Do not make threats"
      ],
      "next_possible_nodes": [
        "OUT-01",
        "FAIL-02"
      ]
    }
  ]
}