{
  "node_id": "LA_INP-01",
  "state": "LA",
  "state_name": "Louisiana",
  "node_family": "INP",
  "subnode": "INP-01",
  "trigger_name": "Mandatory Report",
  "summary_html": "**Mandatory reporters** (designated professionals) must report suspected child abuse or neglect. Federal law sets the funding and policy floor (CAPTA) and mandates reporter frameworks on federal lands/facilities (VICAA).",
  "authority_html": "- **CAPTA (42 U.S.C. \u00a7\u00a7 5101\u20135116)** \u2014 federal floor for state reporting systems  \n- **Victims of Child Abuse Act (34 U.S.C. \u00a7\u00a7 20301\u201320307)** \u2014 includes federal-facility reporter duties (recodified from former 42 U.S.C. \u00a713031)",
  "icon": "\ud83d\udcde",
  "theme_color": "#1E90FF",
  "domain": "civil",
  "procedural_weight": 0.4,
  "federal_alignment_flag": "baseline",
  "urls": {
    "CAPTA_Cornell": "https://www.law.cornell.edu/uscode/text/42/chapter-67",
    "CAPTA_House": "https://uscode.house.gov/view.xhtml?path=/prelim@title42/chapter67&edition=prelim",
    "CAPTA_PDF": "https://www.govinfo.gov/content/pkg/USCODE-2021-title42/pdf/USCODE-2021-title42-chap67.pdf",
    "VICAA_Cornell": "https://www.law.cornell.edu/uscode/text/34/subtitle-II/chapter-203",
    "VICAA_House": "https://uscode.house.gov/view.xhtml?path=/prelim@title34/subtitle2/chapter203&edition=prelim",
    "VICAA_PDF": "https://www.govinfo.gov/content/pkg/USCODE-2021-title34/pdf/USCODE-2021-title34-subtitleII-chap203.pdf"
  },
  "layers": {
    "constitutional": {
      "constraints_triggered": [],
      "alignment": "aligned"
    },
    "federal": {
      "requirements_applicable": [
        "42 U.S.C. \u00a7\u00a7 5101\u20135116 (CAPTA)",
        "34 U.S.C. \u00a7\u00a7 20301\u201320307 (Victims of Child Abuse Act)"
      ]
    },
    "state_statutory": {
      "primary_citations": [
        {
          "citation_text": "Louisiana - Children\u2019s Code Article 601 et seq. (Children\u2019s Code \u2013 Child in Need of Care, includes reporting duties)",
          "source_url": "https://www.legis.la.gov/legis/Laws_Toc.aspx",
          "authority_type": "state_statute",
          "last_verified": "2025-12-22",
          "deep_link": true
        }
      ]
    },
    "administrative_rule": {
      "regulations_applicable": [
        {
          "title": "Title 67 - SOCIAL SERVICES",
          "url": "https://www.law.cornell.edu/regulations/louisiana/title-67"
        },
        {
          "title": "Louisiana Administrative Regulations",
          "url": "https://regulations.justia.com/states/louisiana/",
          "authority_type": "administrative_rule",
          "last_verified": "2025-12-24"
        },
        {
          "title": "Louisiana Administrative Rule Title 1",
          "url": "https://regulations.justia.com/states/louisiana/title-1/",
          "authority_type": "administrative_rule",
          "last_verified": "2025-12-24"
        },
        {
          "title": "Louisiana Administrative Rule Title 2",
          "url": "https://regulations.justia.com/states/louisiana/title-2/",
          "authority_type": "administrative_rule",
          "last_verified": "2025-12-24"
        },
        {
          "title": "Louisiana Administrative Rule Title 3",
          "url": "https://regulations.justia.com/states/louisiana/title-3/",
          "authority_type": "administrative_rule",
          "last_verified": "2025-12-24"
        },
        {
          "title": "Louisiana Administrative Rule Title 4",
          "url": "https://regulations.justia.com/states/louisiana/title-4/",
          "authority_type": "administrative_rule",
          "last_verified": "2025-12-24"
        },
        {
          "title": "Louisiana Administrative Rule Title 5",
          "url": "https://regulations.justia.com/states/louisiana/title-5/",
          "authority_type": "administrative_rule",
          "last_verified": "2025-12-24"
        },
        {
          "title": "Louisiana Administrative Rule Title 6",
          "url": "https://regulations.justia.com/states/louisiana/title-6/",
          "authority_type": "administrative_rule",
          "last_verified": "2025-12-24"
        },
        {
          "title": "Louisiana Administrative Rule Title 7",
          "url": "https://regulations.justia.com/states/louisiana/title-7/",
          "authority_type": "administrative_rule",
          "last_verified": "2025-12-24"
        },
        {
          "title": "Louisiana Administrative Rule Title 8",
          "url": "https://regulations.justia.com/states/louisiana/title-8/",
          "authority_type": "administrative_rule",
          "last_verified": "2025-12-24"
        },
        {
          "title": "Louisiana Administrative Rule Title 9",
          "url": "https://regulations.justia.com/states/louisiana/title-9/",
          "authority_type": "administrative_rule",
          "last_verified": "2025-12-24"
        }
      ],
      "source_url": "https://www.law.cornell.edu/regulations/louisiana.html"
    },
    "state_constitutional": {
      "plane_reference": "state_constitutional_LA",
      "plane_file": "legal_planes/state_constitutional/LA_constitution.json",
      "provisions_triggered": []
    },
    "case_law": {
      "search_keywords": [
        "Louisiana Department of Children and Family Services",
        "DCFS",
        "CPS",
        "due process",
        "14th Amendment",
        "42 U.S.C. 1983",
        "reasonable efforts",
        "reunification",
        "emergency removal",
        "wrongful removal"
      ],
      "courtlistener_search_url": "https://www.courtlistener.com/?q=%22Louisiana%22%20AND%20%28%22Louisiana%20Department%20of%20Children%20and%20Family%20Services%22%20OR%20%22DCFS%22%20OR%20%22CPS%22%20OR%20%22due%20process%22%20OR%20%2214th%20Amendment%22%29&type=o&order_by=score+desc",
      "relevant_case_types": [
        "mandatory reporting",
        "failure to report",
        "reporter immunity",
        "hotline"
      ],
      "jurisdiction": "Louisiana state courts",
      "key_cases": [
        {
          "case_id": "2025-b-00537",
          "title": "IN RE: HENRY L. KLEIN",
          "url": "https://law.justia.com/cases/louisiana/supreme-court/2025/2025-b-00537.html",
          "year": 2025,
          "court": "Supreme Court",
          "citation": "Louisiana Supreme Court Case 2025-b-00537 (2025)",
          "relevance_score": 1.0,
          "matched_keywords": [
            "child welfare"
          ],
          "child_welfare_reason": "High: In re name, In re"
        },
        {
          "case_id": "2025-o-00994",
          "title": "IN RE: JUDGE ROYALE COLBERT",
          "url": "https://law.justia.com/cases/louisiana/supreme-court/2025/2025-o-00994.html",
          "year": 2025,
          "court": "Supreme Court",
          "citation": "Louisiana Supreme Court Case 2025-o-00994 (2025)",
          "relevance_score": 1.0,
          "matched_keywords": [
            "child welfare"
          ],
          "child_welfare_reason": "High: In re"
        },
        {
          "case_id": "2025-o-01127",
          "title": "IN RE: JUDGE TIFFANY FOXWORTH-ROBERTS",
          "url": "https://law.justia.com/cases/louisiana/supreme-court/2025/2025-o-01127.html",
          "year": 2025,
          "court": "Supreme Court",
          "citation": "Louisiana Supreme Court Case 2025-o-01127 (2025)",
          "relevance_score": 1.0,
          "matched_keywords": [
            "child welfare"
          ],
          "child_welfare_reason": "High: In re"
        },
        {
          "case_id": "2025-o-00879",
          "title": "IN RE: JUDGE JENNIFER M. MEDLEY",
          "url": "https://law.justia.com/cases/louisiana/supreme-court/2025/2025-o-00879.html",
          "year": 2025,
          "court": "Supreme Court",
          "citation": "Louisiana Supreme Court Case 2025-o-00879 (2025)",
          "relevance_score": 1.0,
          "matched_keywords": [
            "child welfare"
          ],
          "child_welfare_reason": "High: In re"
        },
        {
          "case_id": "2025-o-00320",
          "title": "IN RE: JUDGE DONALD \"CHICK\" FORET TWENTY-FOURTH JUDICIAL DISTRICT COURT PARISH OF JEFFERSON STATE OF LOUISIANA",
          "url": "https://law.justia.com/cases/louisiana/supreme-court/2025/2025-o-00320.html",
          "year": 2025,
          "court": "Supreme Court",
          "citation": "Louisiana Supreme Court Case 2025-o-00320 (2025)",
          "relevance_score": 1.0,
          "matched_keywords": [
            "child welfare"
          ],
          "child_welfare_reason": "High: In re"
        },
        {
          "case_id": "2024-ck-00254",
          "title": "In re D.D.",
          "url": "https://law.justia.com/cases/louisiana/supreme-court/2025/2024-ck-00254.html",
          "year": 2025,
          "court": "Supreme Court",
          "citation": "Louisiana Supreme Court Case 2024-ck-00254 (2025)",
          "relevance_score": 1.0,
          "matched_keywords": [
            "child welfare"
          ],
          "child_welfare_reason": "High: In re initials"
        },
        {
          "case_id": "2023-ba-00159",
          "title": "IN RE: COMMITTEE ON BAR ADMISSIONS CFN-1791",
          "url": "https://law.justia.com/cases/louisiana/supreme-court/2025/2023-ba-00159.html",
          "year": 2025,
          "court": "Supreme Court",
          "citation": "Louisiana Supreme Court Case 2023-ba-00159 (2025)",
          "relevance_score": 1.0,
          "matched_keywords": [
            "child welfare"
          ],
          "child_welfare_reason": "High: In re"
        },
        {
          "case_id": "2023-ba-01455",
          "title": "IN RE: COMMITTEE ON BAR ADMISSIONS CFN-65372",
          "url": "https://law.justia.com/cases/louisiana/supreme-court/2024/2023-ba-01455.html",
          "year": 2024,
          "court": "Supreme Court",
          "citation": "Louisiana Supreme Court Case 2023-ba-01455 (2024)",
          "relevance_score": 1.0,
          "matched_keywords": [
            "child welfare"
          ],
          "child_welfare_reason": "High: In re"
        },
        {
          "case_id": "2024-b-00479",
          "title": "IN RE: TRINA TRINHTHI CHU",
          "url": "https://law.justia.com/cases/louisiana/supreme-court/2024/2024-b-00479.html",
          "year": 2024,
          "court": "Supreme Court",
          "citation": "Louisiana Supreme Court Case 2024-b-00479 (2024)",
          "relevance_score": 1.0,
          "matched_keywords": [
            "child welfare"
          ],
          "child_welfare_reason": "High: In re"
        },
        {
          "case_id": "2024-b-00520",
          "title": "IN RE: NED FRANKLIN PIERCE SONNIER, SR.",
          "url": "https://law.justia.com/cases/louisiana/supreme-court/2024/2024-b-00520.html",
          "year": 2024,
          "court": "Supreme Court",
          "citation": "Louisiana Supreme Court Case 2024-b-00520 (2024)",
          "relevance_score": 1.0,
          "matched_keywords": [
            "child welfare"
          ],
          "child_welfare_reason": "High: In re"
        }
      ],
      "_note": "Use search URL to find relevant cases on CourtListener"
    }
  },
  "state_agency": {
    "name": "Department of Children and Family Services",
    "acronym": "DCFS",
    "hotline": "1-855-452-5437",
    "website": "https://www.legis.la.gov"
  },
  "mandatory_reporters": [
    "Teachers/School Personnel",
    "Medical/Dental Professionals",
    "Mental Health Professionals",
    "Law Enforcement",
    "Childcare Staff",
    "Clergy",
    "Foster Parents",
    "Coaches",
    "Coroners",
    "EMTs/Emergency Personnel"
  ],
  "reporting_type": "centralized",
  "reporting_details": "Not applicable",
  "definitions": {
    "abuse": [
      "Physical abuse",
      "Sexual abuse",
      "Emotional abuse",
      "Excessive punishment",
      "Shaken baby syndrome",
      "Human trafficking",
      "Domestic violence exposure",
      "Failure to protect",
      "Female genital mutilation",
      "Factitious disorder (Munchausen by proxy)",
      "Institutional abuse/neglect"
    ],
    "neglect": [
      "General neglect",
      "Medical neglect",
      "Abandonment",
      "Inadequate supervision",
      "Inadequate shelter/housing",
      "Inadequate clothing",
      "Malnourishment/failure to provide food",
      "Failure to thrive",
      "Injurious environment"
    ],
    "other": [
      "Coerced abortion"
    ],
    "substance_related": [
      "Drug lab exposure",
      "Parental drug/alcohol misuse",
      "Prenatal drug/alcohol exposure",
      "Illicit substance involvement"
    ]
  },
  "_metadata": {
    "created": "2025-12-22T19:33:40.756268",
    "source": "real_data_etl",
    "data_sources": [
      "SCAN_2023",
      "CSE_DomainMap",
      "state_sources",
      "federal_baseline"
    ],
    "federal_baseline": true,
    "state_specific": true,
    "schema_v3_updated": "2025-12-22T22:17:51.632475",
    "schema_version": "3.0.0",
    "leaves_linked": "2025-12-24T18:14:21.546273+00:00",
    "leaf_linker_version": "1.0.0"
  },
  "burden_of_proof": {
    "standard": "reasonable_suspicion",
    "who_bears_burden": "agency",
    "common_failures": [
      "Insufficient screening documentation",
      "Failure to verify reporter allegations",
      "Accepting anonymous reports without corroboration"
    ]
  },
  "timeline_requirements": [
    {
      "requirement_name": "Initial response time",
      "deadline": "24-72 hours",
      "starts_from": "Report received",
      "source": "state_statute",
      "consequence_of_miss": "Potential audit finding, CFSR deficiency"
    },
    {
      "requirement_name": "Investigation completion",
      "deadline": "30-60 days",
      "starts_from": "Investigation opened",
      "source": "state_statute",
      "consequence_of_miss": "Case dismissal risk"
    }
  ],
  "notice_requirements": [
    {
      "who_must_be_notified": [
        "parent",
        "legal_guardian"
      ],
      "method": "any_reasonable",
      "timing": "Before investigation interview",
      "content_required": [
        "Nature of allegation",
        "Rights"
      ],
      "defective_notice_consequence": "May invalidate findings"
    }
  ],
  "door_scenarios": [
    {
      "who_at_door": [
        "caseworker"
      ],
      "trigger_reason": "Responding to abuse/neglect report",
      "legal_authority_to_enter": "none_without_consent",
      "parent_rights_at_moment": [
        "Right to refuse entry without warrant",
        "Right to remain silent",
        "Right to attorney"
      ],
      "what_to_say": [
        "I do not consent to entry without a warrant",
        "Please provide your card and the allegations in writing",
        "I will have my attorney contact you"
      ],
      "what_not_to_do": [
        "Do not physically resist",
        "Do not lie",
        "Do not let them in 'just to look'"
      ],
      "next_possible_nodes": [
        "DEC-01",
        "DEC-04"
      ]
    }
  ]
}